<?xml version="1.0" encoding="UTF-8" standalone="yes"?>
<?xml-stylesheet href="http://werdis.dwd.de/css/UNIDART/climateTimeseriesOrderByStation.xsl" type="text/xsl"?>
<data xmlns="http://www.unidart.eu/xsd"
  xmlns:xsi="http://www.w3.org/2001/XMLSchema-instance"
  xsi:schemaLocation="http://www.unidart.eu/xsd
     http://werdis.dwd.de/conf/timeseriesExchangeType.xsd">
<stationname value="Keula">
    <v date="1900-08" qualityLevel="unknown" latitude="51.3342" longitude="10.5336" altitude="431" unitA="m" geoQualityLevel="uncertain" unitV="mm" sensorHeightAboveGround="">61.0</v>
    <v date="1900-09">29.0</v>
    <v date="1900-10">83.0</v>
    <v date="1900-11">44.0</v>
    <v date="1900-12">71.0</v>
    <v date="1901-01">70.0</v>
    <v date="1901-02">35.0</v>
    <v date="1901-03">43.0</v>
    <v date="1901-05">30.0</v>
    <v date="1901-06">54.0</v>
    <v date="1901-07">98.0</v>
    <v date="1901-08">18.0</v>
    <v date="1901-09">84.0</v>
    <v date="1901-12">73.0</v>
    <v date="1902-01">80.0</v>
    <v date="1902-02">42.0</v>
    <v date="1902-03">79.0</v>
    <v date="1902-04">32.0</v>
    <v date="1902-05">106.0</v>
    <v date="1902-06">59.0</v>
    <v date="1902-07">82.0</v>
    <v date="1902-08">118.0</v>
    <v date="1902-09">44.0</v>
    <v date="1902-10">65.0</v>
    <v date="1902-11">6.0</v>
    <v date="1902-12">118.0</v>
    <v date="1903-01">42.0</v>
    <v date="1903-02">31.0</v>
    <v date="1903-03">45.0</v>
    <v date="1903-04">103.0</v>
    <v date="1903-05">79.0</v>
    <v date="1903-06">51.0</v>
    <v date="1903-07">81.0</v>
    <v date="1903-08">125.0</v>
    <v date="1903-09">81.0</v>
    <v date="1903-10">73.0</v>
    <v date="1903-11">97.0</v>
    <v date="1903-12">14.0</v>
    <v date="1904-01">39.0</v>
    <v date="1904-02">79.0</v>
    <v date="1904-03">47.0</v>
    <v date="1904-04">48.0</v>
    <v date="1904-05">81.0</v>
    <v date="1904-06">64.0</v>
    <v date="1904-07">41.0</v>
    <v date="1904-08">24.0</v>
    <v date="1904-11">120.0</v>
    <v date="1904-12">82.0</v>
    <v date="1905-01">60.0</v>
    <v date="1905-02">63.0</v>
    <v date="1905-03">82.0</v>
    <v date="1905-04">62.0</v>
    <v date="1905-05">36.0</v>
    <v date="1905-06">60.0</v>
    <v date="1905-07">137.0</v>
    <v date="1905-08">44.0</v>
    <v date="1905-09">81.0</v>
    <v date="1905-10">96.0</v>
    <v date="1905-11">42.0</v>
    <v date="1905-12">28.0</v>
    <v date="1906-01">65.0</v>
    <v date="1906-02">78.0</v>
    <v date="1906-03">109.0</v>
    <v date="1906-04">19.0</v>
    <v date="1906-05">79.0</v>
    <v date="1906-06">58.0</v>
    <v date="1906-07">92.0</v>
    <v date="1906-08">62.0</v>
    <v date="1906-09">47.0</v>
    <v date="1906-10">34.0</v>
    <v date="1906-11">53.0</v>
    <v date="1906-12">96.0</v>
    <v date="1907-01">55.0</v>
    <v date="1907-02">54.0</v>
    <v date="1907-03">62.0</v>
    <v date="1907-04">27.0</v>
    <v date="1907-05">79.0</v>
    <v date="1907-06">64.0</v>
    <v date="1907-07">127.0</v>
    <v date="1907-08">86.0</v>
    <v date="1907-09">37.0</v>
    <v date="1907-10">30.0</v>
    <v date="1907-11">39.0</v>
    <v date="1907-12">64.0</v>
    <v date="1908-01">40.0</v>
    <v date="1908-02">95.0</v>
    <v date="1908-03">41.0</v>
    <v date="1908-04">89.0</v>
    <v date="1908-05">79.0</v>
    <v date="1908-06">38.0</v>
    <v date="1908-07">54.0</v>
    <v date="1908-08">90.0</v>
    <v date="1908-09">44.0</v>
    <v date="1908-10">2.0</v>
    <v date="1908-11">41.0</v>
    <v date="1908-12">9.0</v>
    <v date="1909-01">45.0</v>
    <v date="1909-02">115.0</v>
    <v date="1909-03">32.0</v>
    <v date="1909-04">57.0</v>
    <v date="1909-05">28.0</v>
    <v date="1909-06">55.0</v>
    <v date="1909-07">83.0</v>
    <v date="1909-08">47.0</v>
    <v date="1909-09">146.0</v>
    <v date="1909-10">72.0</v>
    <v date="1909-11">105.0</v>
    <v date="1909-12">67.0</v>
    <v date="1910-01">49.0</v>
    <v date="1910-02">49.0</v>
    <v date="1910-03">25.0</v>
    <v date="1910-04">41.0</v>
    <v date="1910-05">46.0</v>
    <v date="1910-06">84.0</v>
    <v date="1910-07">69.0</v>
    <v date="1910-08">74.0</v>
    <v date="1910-09">43.0</v>
    <v date="1910-10">20.0</v>
    <v date="1910-11">81.0</v>
    <v date="1910-12">48.0</v>
    <v date="1911-01">31.0</v>
    <v date="1911-02">72.0</v>
    <v date="1911-03">38.0</v>
    <v date="1911-04">25.0</v>
    <v date="1911-05">29.0</v>
    <v date="1911-06">38.0</v>
    <v date="1911-07">56.0</v>
    <v date="1911-08">27.0</v>
    <v date="1911-09">19.0</v>
    <v date="1911-10">27.0</v>
    <v date="1911-11">30.0</v>
    <v date="1911-12">70.0</v>
    <v date="1912-01">65.0</v>
    <v date="1912-02">45.0</v>
    <v date="1912-03">61.0</v>
    <v date="1912-04">34.0</v>
    <v date="1912-05">75.0</v>
    <v date="1912-06">64.0</v>
    <v date="1912-07">60.0</v>
    <v date="1912-08">124.0</v>
    <v date="1912-09">57.0</v>
    <v date="1912-10">49.0</v>
    <v date="1912-11">94.0</v>
    <v date="1912-12">70.0</v>
    <v date="1913-01">48.0</v>
    <v date="1913-02">39.0</v>
    <v date="1913-03">60.0</v>
    <v date="1913-04">39.0</v>
    <v date="1913-05">102.0</v>
    <v date="1913-06">69.0</v>
    <v date="1913-07">26.0</v>
    <v date="1913-08">53.0</v>
    <v date="1913-09">50.0</v>
    <v date="1913-10">39.0</v>
    <v date="1913-11">75.0</v>
    <v date="1913-12">128.0</v>
    <v date="1914-01">37.0</v>
    <v date="1914-02">28.0</v>
    <v date="1914-03">102.0</v>
    <v date="1914-04">15.0</v>
    <v date="1914-05">106.0</v>
    <v date="1914-06">67.0</v>
    <v date="1914-07">92.0</v>
    <v date="1914-08">19.0</v>
    <v date="1914-09">69.0</v>
    <v date="1914-10">71.0</v>
    <v date="1914-11">41.0</v>
    <v date="1914-12">57.0</v>
    <v date="1915-01">104.0</v>
    <v date="1915-02">29.0</v>
    <v date="1915-03">112.0</v>
    <v date="1915-04">33.0</v>
    <v date="1915-05">19.0</v>
    <v date="1915-06">28.0</v>
    <v date="1915-07">37.0</v>
    <v date="1915-08">100.0</v>
    <v date="1915-09">34.0</v>
    <v date="1915-10">48.0</v>
    <v date="1915-11">45.0</v>
    <v date="1915-12">110.0</v>
    <v date="1916-01">84.0</v>
    <v date="1916-02">87.0</v>
    <v date="1916-03">55.0</v>
    <v date="1916-04">63.0</v>
    <v date="1916-05">45.0</v>
    <v date="1916-06">61.0</v>
    <v date="1916-07">85.0</v>
    <v date="1916-08">65.0</v>
    <v date="1916-09">55.0</v>
    <v date="1916-10">44.0</v>
    <v date="1916-11">25.0</v>
    <v date="1916-12">74.0</v>
    <v date="1917-01">72.0</v>
    <v date="1917-02">14.0</v>
    <v date="1917-03">64.0</v>
    <v date="1917-04">67.0</v>
    <v date="1917-05">38.0</v>
    <v date="1917-06">34.0</v>
    <v date="1917-07">40.0</v>
    <v date="1917-08">160.0</v>
    <v date="1917-09">12.0</v>
    <v date="1917-10">90.0</v>
    <v date="1917-11">48.0</v>
    <v date="1917-12">51.0</v>
    <v date="1918-01">98.0</v>
    <v date="1918-02">52.0</v>
    <v date="1918-03">25.0</v>
    <v date="1918-04">70.0</v>
    <v date="1918-05">23.0</v>
    <v date="1918-06">55.0</v>
    <v date="1918-07">108.0</v>
    <v date="1918-08">108.0</v>
    <v date="1918-09">56.0</v>
    <v date="1918-10">84.0</v>
    <v date="1918-11">19.0</v>
    <v date="1918-12">85.0</v>
    <v date="1919-01">31.0</v>
    <v date="1919-02">19.0</v>
    <v date="1919-03">49.0</v>
    <v date="1919-04">65.0</v>
    <v date="1919-05">14.0</v>
    <v date="1919-06">42.0</v>
    <v date="1919-07">62.0</v>
    <v date="1919-08">29.0</v>
    <v date="1919-09">35.0</v>
    <v date="1919-10">45.0</v>
    <v date="1919-11">119.0</v>
    <v date="1919-12">117.0</v>
    <v date="1920-01">77.0</v>
    <v date="1920-02">36.0</v>
    <v date="1920-03">23.0</v>
    <v date="1920-04">48.0</v>
    <v date="1920-05">84.0</v>
    <v date="1920-06">33.0</v>
    <v date="1920-07">83.0</v>
    <v date="1920-08">65.0</v>
    <v date="1920-09">67.0</v>
    <v date="1920-10">12.0</v>
    <v date="1920-11">23.0</v>
    <v date="1920-12">41.0</v>
    <v date="1921-01">130.0</v>
    <v date="1921-02">23.0</v>
    <v date="1921-03">8.0</v>
    <v date="1921-04">22.0</v>
    <v date="1921-05">139.0</v>
    <v date="1921-06">48.0</v>
    <v date="1921-07">53.0</v>
    <v date="1921-08">37.0</v>
    <v date="1921-09">35.0</v>
    <v date="1921-10">45.0</v>
    <v date="1921-11">39.0</v>
    <v date="1921-12">50.0</v>
    <v date="1922-01">76.0</v>
    <v date="1922-02">46.0</v>
    <v date="1922-03">57.0</v>
    <v date="1922-04">107.0</v>
    <v date="1922-05">53.0</v>
    <v date="1922-06">43.0</v>
    <v date="1922-07">100.0</v>
    <v date="1922-08">70.0</v>
    <v date="1922-09">77.0</v>
    <v date="1922-10">81.0</v>
    <v date="1922-11">126.0</v>
    <v date="1922-12">64.0</v>
    <v date="1923-01">63.0</v>
    <v date="1923-02">48.0</v>
    <v date="1923-03">39.0</v>
    <v date="1923-04">53.0</v>
    <v date="1923-05">112.0</v>
    <v date="1923-06">66.0</v>
    <v date="1923-07">65.0</v>
    <v date="1923-08">39.0</v>
    <v date="1923-09">50.0</v>
    <v date="1923-10">186.0</v>
    <v date="1923-11">32.0</v>
    <v date="1923-12">75.0</v>
    <v date="1924-01">24.0</v>
    <v date="1924-02">47.0</v>
    <v date="1924-03">28.0</v>
    <v date="1924-04">88.0</v>
    <v date="1924-05">46.0</v>
    <v date="1924-06">79.0</v>
    <v date="1924-07">76.0</v>
    <v date="1924-08">118.0</v>
    <v date="1924-09">139.0</v>
    <v date="1924-10">33.0</v>
    <v date="1924-11">25.0</v>
    <v date="1924-12">34.0</v>
    <v date="1925-01">59.0</v>
    <v date="1925-02">54.0</v>
    <v date="1925-03">52.0</v>
    <v date="1925-04">99.0</v>
    <v date="1925-05">13.0</v>
    <v date="1925-06">49.0</v>
    <v date="1925-07">86.0</v>
    <v date="1925-08">90.0</v>
    <v date="1925-09">92.0</v>
    <v date="1925-10">52.0</v>
    <v date="1925-11">58.0</v>
    <v date="1925-12">103.0</v>
    <v date="1926-01">70.0</v>
    <v date="1926-02">66.0</v>
    <v date="1926-03">89.0</v>
    <v date="1926-04">42.0</v>
    <v date="1926-05">38.0</v>
    <v date="1926-06">102.0</v>
    <v date="1926-07">230.0</v>
    <v date="1926-08">71.0</v>
    <v date="1926-09">36.0</v>
    <v date="1926-10">115.0</v>
    <v date="1926-11">31.0</v>
    <v date="1926-12">48.0</v>
    <v date="1927-01">56.0</v>
    <v date="1927-02">26.0</v>
    <v date="1927-03">36.0</v>
    <v date="1927-04">152.0</v>
    <v date="1927-05">51.0</v>
    <v date="1927-06">63.0</v>
    <v date="1927-07">140.0</v>
    <v date="1927-08">219.0</v>
    <v date="1927-09">59.0</v>
    <v date="1927-10">39.0</v>
    <v date="1927-11">52.0</v>
    <v date="1927-12">29.0</v>
    <v date="1928-01">51.0</v>
    <v date="1928-02">47.0</v>
    <v date="1928-03">40.0</v>
    <v date="1928-04">100.0</v>
    <v date="1928-05">53.0</v>
    <v date="1928-06">32.0</v>
    <v date="1928-07">73.0</v>
    <v date="1928-08">45.0</v>
    <v date="1928-09">29.0</v>
    <v date="1928-10">77.0</v>
    <v date="1928-11">125.0</v>
    <v date="1928-12">56.0</v>
    <v date="1929-01">37.0</v>
    <v date="1929-02">21.0</v>
    <v date="1929-03">12.0</v>
    <v date="1929-04">67.0</v>
    <v date="1929-05">40.0</v>
    <v date="1929-06">71.0</v>
    <v date="1929-07">61.0</v>
    <v date="1929-08">27.0</v>
    <v date="1929-09">25.0</v>
    <v date="1929-10">99.0</v>
    <v date="1929-11">31.0</v>
    <v date="1929-12">83.0</v>
    <v date="1930-01">33.0</v>
    <v date="1930-02">5.0</v>
    <v date="1930-03">38.0</v>
    <v date="1930-04">75.0</v>
    <v date="1930-05">50.0</v>
    <v date="1930-06">34.0</v>
    <v date="1930-07">74.0</v>
    <v date="1930-08">57.0</v>
    <v date="1930-09">60.0</v>
    <v date="1930-10">75.0</v>
    <v date="1930-11">109.0</v>
    <v date="1930-12">20.0</v>
    <v date="1931-01">91.0</v>
    <v date="1931-02">33.0</v>
    <v date="1931-03">36.0</v>
    <v date="1931-04">65.0</v>
    <v date="1931-05">40.0</v>
    <v date="1931-06">64.0</v>
    <v date="1931-07">112.0</v>
    <v date="1931-08">97.0</v>
    <v date="1931-09">66.0</v>
    <v date="1931-10">54.0</v>
    <v date="1931-11">19.0</v>
    <v date="1931-12">66.0</v>
    <v date="1932-01">64.0</v>
    <v date="1932-02">32.0</v>
    <v date="1932-03">38.0</v>
    <v date="1932-04">77.0</v>
    <v date="1932-05">102.0</v>
    <v date="1932-06">42.0</v>
    <v date="1932-07">57.0</v>
    <v date="1932-08">27.0</v>
    <v date="1932-09">73.0</v>
    <v date="1932-10">101.0</v>
    <v date="1932-11">67.0</v>
    <v date="1932-12">1.0</v>
    <v date="1933-01">39.0</v>
    <v date="1933-02">41.0</v>
    <v date="1933-03">28.0</v>
    <v date="1933-04">28.0</v>
    <v date="1933-05">51.0</v>
    <v date="1933-06">140.0</v>
    <v date="1933-07">80.0</v>
    <v date="1933-08">57.0</v>
    <v date="1933-09">32.0</v>
    <v date="1933-10">45.0</v>
    <v date="1933-11">32.0</v>
    <v date="1933-12">26.0</v>
    <v date="1934-01">30.0</v>
    <v date="1934-02">52.0</v>
    <v date="1934-03">20.0</v>
    <v date="1934-04">10.0</v>
    <v date="1934-05">47.0</v>
    <v date="1934-06">59.0</v>
    <v date="1934-07">78.0</v>
    <v date="1934-08">48.0</v>
    <v date="1934-09">16.0</v>
    <v date="1934-10">110.0</v>
    <v date="1934-11">47.0</v>
    <v date="1934-12">47.0</v>
    <v date="1935-01">70.0</v>
    <v date="1935-02">81.0</v>
    <v date="1935-03">37.0</v>
    <v date="1935-04">125.0</v>
    <v date="1935-05">36.0</v>
    <v date="1935-06">82.0</v>
    <v date="1935-07">35.0</v>
    <v date="1935-08">60.0</v>
    <v date="1935-09">51.0</v>
    <v date="1935-10">86.0</v>
    <v date="1935-11">18.0</v>
    <v date="1935-12">39.0</v>
    <v date="1936-01">47.0</v>
    <v date="1936-02">76.0</v>
    <v date="1936-03">18.0</v>
    <v date="1936-04">54.0</v>
    <v date="1936-05">47.0</v>
    <v date="1936-06">38.0</v>
    <v date="1936-07">101.0</v>
    <v date="1936-08">48.0</v>
    <v date="1936-09">53.0</v>
    <v date="1936-10">88.0</v>
    <v date="1936-11">45.0</v>
    <v date="1936-12">50.0</v>
    <v date="1937-01">47.0</v>
    <v date="1937-02">102.0</v>
    <v date="1937-03">46.0</v>
    <v date="1937-04">67.0</v>
    <v date="1937-05">43.0</v>
    <v date="1937-06">87.0</v>
    <v date="1937-07">87.0</v>
    <v date="1937-08">34.0</v>
    <v date="1937-09">34.0</v>
    <v date="1937-10">29.0</v>
    <v date="1937-11">33.0</v>
    <v date="1937-12">51.0</v>
    <v date="1938-01">132.0</v>
    <v date="1938-02">39.0</v>
    <v date="1938-03">23.0</v>
    <v date="1938-04">33.0</v>
    <v date="1938-05">94.0</v>
    <v date="1938-06">55.0</v>
    <v date="1938-07">92.0</v>
    <v date="1938-08">56.0</v>
    <v date="1938-09">34.0</v>
    <v date="1938-10">54.0</v>
    <v date="1938-11">33.0</v>
    <v date="1938-12">52.0</v>
    <v date="1939-01">62.0</v>
    <v date="1939-02">32.0</v>
    <v date="1939-03">90.0</v>
    <v date="1939-04">72.0</v>
    <v date="1939-05">57.0</v>
    <v date="1939-06">25.0</v>
    <v date="1939-07">58.0</v>
    <v date="1939-08">77.0</v>
    <v date="1939-09">56.0</v>
    <v date="1939-10">106.0</v>
    <v date="1939-11">117.0</v>
    <v date="1939-12">43.0</v>
    <v date="1940-01">33.0</v>
    <v date="1940-02">22.0</v>
    <v date="1940-03">85.0</v>
    <v date="1940-04">59.0</v>
    <v date="1940-05">20.0</v>
    <v date="1940-06">37.0</v>
    <v date="1940-07">144.0</v>
    <v date="1940-08">90.0</v>
    <v date="1940-09">85.0</v>
    <v date="1940-10">38.0</v>
    <v date="1940-11">114.0</v>
    <v date="1940-12">91.0</v>
    <v date="1941-01">66.0</v>
    <v date="1941-02">48.0</v>
    <v date="1941-03">63.0</v>
    <v date="1941-04">29.0</v>
    <v date="1941-05">83.0</v>
    <v date="1941-06">66.0</v>
    <v date="1941-07">51.0</v>
    <v date="1941-08">141.0</v>
    <v date="1941-09">50.0</v>
    <v date="1941-10">145.0</v>
    <v date="1941-11">44.0</v>
    <v date="1941-12">71.0</v>
    <v date="1942-01">27.0</v>
    <v date="1942-02">29.0</v>
    <v date="1942-03">39.0</v>
    <v date="1942-04">20.0</v>
    <v date="1942-05">71.0</v>
    <v date="1942-06">68.0</v>
    <v date="1942-07">104.0</v>
    <v date="1942-08">33.0</v>
    <v date="1942-09">41.0</v>
    <v date="1942-10">88.0</v>
    <v date="1942-11">61.0</v>
    <v date="1942-12">33.0</v>
    <v date="1943-01">31.0</v>
    <v date="1943-02">48.0</v>
    <v date="1943-03">14.0</v>
    <v date="1943-04">92.0</v>
    <v date="1943-05">28.0</v>
    <v date="1943-06">72.0</v>
    <v date="1943-07">22.0</v>
    <v date="1943-08">92.0</v>
    <v date="1943-09">59.0</v>
    <v date="1943-10">1.0</v>
    <v date="1943-11">74.0</v>
    <v date="1943-12">38.0</v>
    <v date="1944-01">94.0</v>
    <v date="1944-02">57.0</v>
    <v date="1944-03">77.0</v>
    <v date="1944-04">42.0</v>
    <v date="1944-05">68.0</v>
    <v date="1944-06">82.0</v>
    <v date="1944-07">84.0</v>
    <v date="1944-08">28.0</v>
    <v date="1944-09">52.0</v>
    <v date="1944-10">72.0</v>
    <v date="1944-11">119.0</v>
    <v date="1944-12">63.0</v>
    <v date="1945-01">37.0</v>
    <v date="1945-02">71.0</v>
    <v date="1945-03">36.0</v>
    <v date="1945-04">44.0</v>
    <v date="1945-05">60.0</v>
    <v date="1945-06">92.0</v>
    <v date="1945-07">94.0</v>
    <v date="1945-08">110.0</v>
    <v date="1945-09">42.0</v>
    <v date="1945-10">60.0</v>
    <v date="1945-11">54.0</v>
    <v date="1945-12">85.0</v>
    <v date="1946-01">40.0</v>
    <v date="1946-02">194.0</v>
    <v date="1946-03">35.0</v>
    <v date="1946-04">20.0</v>
    <v date="1946-05">53.0</v>
    <v date="1946-06">128.0</v>
    <v date="1946-07">14.0</v>
    <v date="1946-08">29.0</v>
    <v date="1946-09">77.0</v>
    <v date="1946-10">75.0</v>
    <v date="1946-11">18.0</v>
    <v date="1946-12">31.0</v>
    <v date="1947-01">35.0</v>
    <v date="1947-02">41.0</v>
    <v date="1947-03">64.0</v>
    <v date="1947-04">58.0</v>
    <v date="1947-05">53.0</v>
    <v date="1947-06">69.0</v>
    <v date="1947-07">60.0</v>
    <v date="1947-08">34.0</v>
    <v date="1947-09">23.0</v>
    <v date="1947-10">14.0</v>
    <v date="1947-11">86.0</v>
    <v date="1947-12">136.0</v>
    <v date="1948-01">90.0</v>
    <v date="1948-02">70.0</v>
    <v date="1948-03">20.0</v>
    <v date="1948-04">26.0</v>
    <v date="1948-05">57.0</v>
    <v date="1948-06">62.0</v>
    <v date="1948-07">94.0</v>
    <v date="1948-08">68.0</v>
    <v date="1948-09">19.0</v>
    <v date="1948-10">42.0</v>
    <v date="1948-11">29.0</v>
    <v date="1948-12">18.0</v>
    <v date="1949-01">46.0</v>
    <v date="1949-02">41.0</v>
    <v date="1949-03">64.0</v>
    <v date="1949-04">52.0</v>
    <v date="1949-05">52.0</v>
    <v date="1949-06">66.0</v>
    <v date="1949-07">16.0</v>
    <v date="1949-08">84.0</v>
    <v date="1949-09">16.0</v>
    <v date="1949-10">13.0</v>
    <v date="1949-11">66.0</v>
    <v date="1949-12">83.0</v>
    <v date="1950-01">40.0</v>
    <v date="1950-02">98.0</v>
    <v date="1950-03">11.0</v>
    <v date="1950-04">86.0</v>
    <v date="1950-05">140.0</v>
    <v date="1950-06">40.0</v>
    <v date="1950-07">122.0</v>
    <v date="1950-08">49.0</v>
    <v date="1950-09">45.0</v>
    <v date="1950-10">38.0</v>
    <v date="1950-11">64.0</v>
    <v date="1950-12">59.0</v>
    <v date="1951-01">52.2</v>
    <v date="1951-02">30.1</v>
    <v date="1951-03">41.2</v>
    <v date="1951-04">32.2</v>
    <v date="1951-05">43.2</v>
    <v date="1951-06">125.9</v>
    <v date="1951-07">51.1</v>
    <v date="1951-08">66.1</v>
    <v date="1951-09">45.3</v>
    <v date="1951-10">26.6</v>
    <v date="1951-11">91.9</v>
    <v date="1951-12">28.0</v>
    <v date="1952-01">81.9</v>
    <v date="1952-02">51.3</v>
    <v date="1952-03">98.3</v>
    <v date="1952-04">11.8</v>
    <v date="1952-05">63.3</v>
    <v date="1952-06">50.9</v>
    <v date="1952-07">37.2</v>
    <v date="1952-08">59.9</v>
    <v date="1952-09">128.9</v>
    <v date="1952-10">106.8</v>
    <v date="1952-11">110.9</v>
    <v date="1952-12">54.2</v>
    <v date="1953-01">56.6</v>
    <v date="1953-02">46.4</v>
    <v date="1953-03">7.2</v>
    <v date="1953-04">18.6</v>
    <v date="1953-05">53.5</v>
    <v date="1953-06">74.3</v>
    <v date="1953-07">85.2</v>
    <v date="1953-08">31.0</v>
    <v date="1953-09">48.4</v>
    <v date="1953-10">43.8</v>
    <v date="1953-11">6.8</v>
    <v date="1953-12">27.0</v>
    <v date="1954-01">85.9</v>
    <v date="1954-02">19.8</v>
    <v date="1954-03">16.7</v>
    <v date="1954-04">37.8</v>
    <v date="1954-05">37.0</v>
    <v date="1954-06">33.8</v>
    <v date="1954-07">111.6</v>
    <v date="1954-08">82.2</v>
    <v date="1954-09">77.5</v>
    <v date="1954-10">49.6</v>
    <v date="1954-11">20.0</v>
    <v date="1954-12">79.3</v>
    <v date="1955-01">63.8</v>
    <v date="1955-02">51.0</v>
    <v date="1955-03">42.3</v>
    <v date="1955-04">32.5</v>
    <v date="1955-05">50.7</v>
    <v date="1955-06">106.7</v>
    <v date="1955-07">132.2</v>
    <v date="1955-08">49.5</v>
    <v date="1955-09">46.8</v>
    <v date="1955-10">55.1</v>
    <v date="1955-11">15.2</v>
    <v date="1955-12">64.4</v>
    <v date="1956-01">48.2</v>
    <v date="1956-02">28.0</v>
    <v date="1956-03">47.7</v>
    <v date="1956-04">96.9</v>
    <v date="1956-05">40.9</v>
    <v date="1956-06">179.1</v>
    <v date="1956-07">197.8</v>
    <v date="1956-08">64.3</v>
    <v date="1956-09">35.2</v>
    <v date="1956-10">59.8</v>
    <v date="1956-11">46.2</v>
    <v date="1956-12">38.1</v>
    <v date="1957-01">32.6</v>
    <v date="1957-02">73.3</v>
    <v date="1957-03">40.8</v>
    <v date="1957-04">33.4</v>
    <v date="1957-05">36.8</v>
    <v date="1957-06">42.0</v>
    <v date="1957-07">96.0</v>
    <v date="1957-08">84.9</v>
    <v date="1957-09">105.5</v>
    <v date="1957-10">20.6</v>
    <v date="1957-11">35.3</v>
    <v date="1957-12">57.3</v>
    <v date="1958-01">56.7</v>
    <v date="1958-02">81.1</v>
    <v date="1958-03">41.4</v>
    <v date="1958-04">41.3</v>
    <v date="1958-05">108.1</v>
    <v date="1958-06">99.3</v>
    <v date="1958-07">59.5</v>
    <v date="1958-08">113.2</v>
    <v date="1958-09">43.7</v>
    <v date="1958-10">55.2</v>
    <v date="1958-11">23.5</v>
    <v date="1958-12">76.9</v>
    <v date="1959-01">57.5</v>
    <v date="1959-02">13.7</v>
    <v date="1959-03">12.8</v>
    <v date="1959-04">34.9</v>
    <v date="1959-05">22.9</v>
    <v date="1959-06">50.5</v>
    <v date="1959-07">64.2</v>
    <v date="1959-08">61.8</v>
    <v date="1959-09">0.5</v>
    <v date="1959-10">34.3</v>
    <v date="1959-11">35.3</v>
    <v date="1959-12">29.0</v>
    <v date="1960-01">84.0</v>
    <v date="1960-02">16.7</v>
    <v date="1960-03">19.4</v>
    <v date="1960-04">32.3</v>
    <v date="1960-05">118.7</v>
    <v date="1960-06">29.7</v>
    <v date="1960-07">59.1</v>
    <v date="1960-08">109.3</v>
    <v date="1960-09">40.1</v>
    <v date="1960-10">97.2</v>
    <v date="1960-11">42.5</v>
    <v date="1960-12">73.8</v>
    <v date="1961-01">63.9</v>
    <v date="1961-02">58.2</v>
    <v date="1961-03">33.3</v>
    <v date="1961-04">110.9</v>
    <v date="1961-05">132.4</v>
    <v date="1961-06">56.9</v>
    <v date="1961-07">74.8</v>
    <v date="1961-08">37.6</v>
    <v date="1961-09">27.5</v>
    <v date="1961-10">30.5</v>
    <v date="1961-11">61.8</v>
    <v date="1961-12">96.2</v>
    <v date="1962-01">40.9</v>
    <v date="1962-02">81.9</v>
    <v date="1962-03">60.6</v>
    <v date="1962-04">56.8</v>
    <v date="1962-05">35.6</v>
    <v date="1962-06">56.9</v>
    <v date="1962-07">84.5</v>
    <v date="1962-08">53.3</v>
    <v date="1962-09">35.0</v>
    <v date="1962-10">8.1</v>
    <v date="1962-11">25.4</v>
    <v date="1962-12">69.4</v>
    <v date="1963-01">34.4</v>
    <v date="1963-02">13.2</v>
    <v date="1963-03">36.1</v>
    <v date="1963-04">29.6</v>
    <v date="1963-05">18.3</v>
    <v date="1963-06">103.2</v>
    <v date="1963-07">45.7</v>
    <v date="1963-08">106.3</v>
    <v date="1963-09">50.6</v>
    <v date="1963-10">24.4</v>
    <v date="1963-11">90.1</v>
    <v date="1963-12">8.7</v>
    <v date="1964-01">24.1</v>
    <v date="1964-02">39.0</v>
    <v date="1964-03">28.6</v>
    <v date="1964-04">41.0</v>
    <v date="1964-05">37.9</v>
    <v date="1964-06">51.0</v>
    <v date="1964-07">30.0</v>
    <v date="1964-08">75.3</v>
    <v date="1964-09">56.6</v>
    <v date="1964-10">37.9</v>
    <v date="1964-11">38.4</v>
    <v date="1964-12">30.3</v>
    <v date="1965-01">63.0</v>
    <v date="1965-02">31.1</v>
    <v date="1965-03">56.7</v>
    <v date="1965-04">73.4</v>
    <v date="1965-05">37.0</v>
    <v date="1965-06">52.4</v>
    <v date="1965-07">122.7</v>
    <v date="1965-08">36.4</v>
    <v date="1965-09">31.7</v>
    <v date="1965-10">19.4</v>
    <v date="1965-11">109.8</v>
    <v date="1965-12">125.9</v>
    <v date="1966-01">51.2</v>
    <v date="1966-02">77.5</v>
    <v date="1966-03">63.4</v>
    <v date="1966-04">70.8</v>
    <v date="1966-05">54.4</v>
    <v date="1966-06">84.2</v>
    <v date="1966-07">65.3</v>
    <v date="1966-08">60.8</v>
    <v date="1966-09">18.7</v>
    <v date="1966-10">90.4</v>
    <v date="1966-11">65.7</v>
    <v date="1966-12">125.8</v>
    <v date="1967-01">41.5</v>
    <v date="1967-02">63.8</v>
    <v date="1967-03">74.2</v>
    <v date="1967-04">65.8</v>
    <v date="1967-05">96.4</v>
    <v date="1967-06">70.6</v>
    <v date="1967-07">62.0</v>
    <v date="1967-08">38.8</v>
    <v date="1967-09">58.2</v>
    <v date="1967-10">45.9</v>
    <v date="1967-11">35.0</v>
    <v date="1967-12">84.4</v>
    <v date="1968-01">96.7</v>
    <v date="1968-02">47.4</v>
    <v date="1968-03">67.6</v>
    <v date="1968-04">43.5</v>
    <v date="1968-05">35.3</v>
    <v date="1968-06">108.1</v>
    <v date="1968-07">30.7</v>
    <v date="1968-08">63.8</v>
    <v date="1968-09">49.0</v>
    <v date="1968-10">39.6</v>
    <v date="1968-11">29.5</v>
    <v date="1969-01">31.6</v>
    <v date="1969-02">42.4</v>
    <v date="1969-03">77.3</v>
    <v date="1969-04">73.8</v>
    <v date="1969-05">84.7</v>
    <v date="1969-06">95.0</v>
    <v date="1969-07">42.9</v>
    <v date="1969-08">94.9</v>
    <v date="1969-09">18.3</v>
    <v date="1969-10">34.4</v>
    <v date="1969-11">60.8</v>
    <v date="1969-12">37.7</v>
    <v date="1970-01">48.4</v>
    <v date="1970-02">109.4</v>
    <v date="1970-03">61.7</v>
    <v date="1970-04">70.7</v>
    <v date="1970-05">73.0</v>
    <v date="1970-06">26.5</v>
    <v date="1970-07">88.1</v>
    <v date="1970-08">71.7</v>
    <v date="1970-09">47.1</v>
    <v date="1970-10">93.2</v>
    <v date="1970-11">49.2</v>
    <v date="1970-12">45.0</v>
    <v date="1971-01">26.7</v>
    <v date="1971-02">27.2</v>
    <v date="1971-03">16.9</v>
    <v date="1971-04">38.8</v>
    <v date="1971-05">134.9</v>
    <v date="1971-06">105.4</v>
    <v date="1971-07">3.8</v>
    <v date="1971-08">21.6</v>
    <v date="1971-09">27.1</v>
    <v date="1971-10">31.0</v>
    <v date="1971-11">46.0</v>
    <v date="1971-12">23.5</v>
    <v date="1972-01">14.3</v>
    <v date="1972-02">3.5</v>
    <v date="1972-03">60.8</v>
    <v date="1972-04">59.2</v>
    <v date="1972-05">100.1</v>
    <v date="1972-06">119.9</v>
    <v date="1972-07">125.4</v>
    <v date="1972-08">103.6</v>
    <v date="1972-09">29.9</v>
    <v date="1972-10">25.3</v>
    <v date="1972-11">50.3</v>
    <v date="1972-12">11.5</v>
    <v date="1973-01">40.0</v>
    <v date="1973-02">53.9</v>
    <v date="1973-03">18.9</v>
    <v date="1973-04">58.7</v>
    <v date="1973-05">50.5</v>
    <v date="1973-06">34.3</v>
    <v date="1973-07">67.8</v>
    <v date="1973-08">16.3</v>
    <v date="1973-09">46.1</v>
    <v date="1973-10">90.1</v>
    <v date="1973-11">53.8</v>
    <v date="1973-12">63.3</v>
    <v date="1974-01">40.5</v>
    <v date="1974-02">36.6</v>
    <v date="1974-03">30.4</v>
    <v date="1974-04">12.4</v>
    <v date="1974-05">61.0</v>
    <v date="1974-06">68.5</v>
    <v date="1974-07">53.1</v>
    <v date="1974-08">64.9</v>
    <v date="1974-09">28.8</v>
    <v date="1974-10">148.5</v>
    <v date="1974-11">59.6</v>
    <v date="1974-12">157.9</v>
    <v date="1975-01">47.6</v>
    <v date="1975-02">15.0</v>
    <v date="1975-03">54.5</v>
    <v date="1975-04">68.1</v>
    <v date="1975-05">83.0</v>
    <v date="1975-06">89.1</v>
    <v date="1975-07">20.4</v>
    <v date="1975-08">36.9</v>
    <v date="1975-09">38.0</v>
    <v date="1975-10">35.1</v>
    <v date="1975-11">53.1</v>
    <v date="1975-12">15.3</v>
    <v date="1976-01">153.1</v>
    <v date="1976-02">26.8</v>
    <v date="1976-03">28.5</v>
    <v date="1976-04">10.7</v>
    <v date="1976-05">40.5</v>
    <v date="1976-06">24.6</v>
    <v date="1976-07">50.0</v>
    <v date="1976-08">25.2</v>
    <v date="1976-09">29.8</v>
    <v date="1976-10">19.1</v>
    <v date="1976-11">55.2</v>
    <v date="1976-12">27.4</v>
    <v date="1977-01">43.5</v>
    <v date="1977-02">49.4</v>
    <v date="1977-03">46.6</v>
    <v date="1977-04">54.1</v>
    <v date="1977-05">23.0</v>
    <v date="1977-06">100.6</v>
    <v date="1977-07">37.0</v>
    <v date="1977-08">126.1</v>
    <v date="1977-09">40.5</v>
    <v date="1977-10">35.5</v>
    <v date="1977-11">96.9</v>
    <v date="1977-12">62.7</v>
    <v date="1978-01">28.1</v>
    <v date="1978-02">22.2</v>
    <v date="1978-03">62.2</v>
    <v date="1978-04">5.9</v>
    <v date="1978-05">94.5</v>
    <v date="1978-06">48.9</v>
    <v date="1978-07">46.8</v>
    <v date="1978-08">75.3</v>
    <v date="1978-09">93.6</v>
    <v date="1978-10">9.8</v>
    <v date="1978-11">2.5</v>
    <v date="1978-12">86.0</v>
    <v date="1979-01">55.4</v>
    <v date="1979-02">42.9</v>
    <v date="1979-03">92.2</v>
    <v date="1979-04">62.6</v>
    <v date="1979-05">54.1</v>
    <v date="1979-06">56.0</v>
    <v date="1979-07">75.9</v>
    <v date="1979-08">27.2</v>
    <v date="1979-09">39.7</v>
    <v date="1979-10">13.3</v>
    <v date="1979-11">86.0</v>
    <v date="1979-12">79.7</v>
    <v date="1980-01">34.0</v>
    <v date="1980-02">56.7</v>
    <v date="1980-03">41.8</v>
    <v date="1980-04">71.3</v>
    <v date="1980-05">41.2</v>
    <v date="1980-06">121.2</v>
    <v date="1980-07">87.0</v>
    <v date="1980-08">47.9</v>
    <v date="1980-09">37.8</v>
    <v date="1980-10">41.1</v>
    <v date="1980-11">51.2</v>
    <v date="1980-12">44.1</v>
    <v date="1981-01" qualityLevel="high">71.0</v>
    <v date="1981-02">25.2</v>
    <v date="1981-03">94.7</v>
    <v date="1981-04">42.3</v>
    <v date="1981-05">91.8</v>
    <v date="1981-06">100.9</v>
    <v date="1981-07">60.2</v>
    <v date="1981-08">84.1</v>
    <v date="1981-09">59.1</v>
    <v date="1981-10">59.1</v>
    <v date="1981-11">92.5</v>
    <v date="1981-12">102.5</v>
    <v date="1982-01">62.5</v>
    <v date="1982-02">1.1</v>
    <v date="1982-03">36.3</v>
    <v date="1982-04">46.5</v>
    <v date="1982-05">56.4</v>
    <v date="1982-06">42.5</v>
    <v date="1982-07">25.7</v>
    <v date="1982-08">16.2</v>
    <v date="1982-09">6.0</v>
    <v date="1982-10">53.9</v>
    <v date="1982-11">22.8</v>
    <v date="1982-12">58.8</v>
    <v date="1983-01">53.9</v>
    <v date="1983-02">29.5</v>
    <v date="1983-03">46.2</v>
    <v date="1983-04">147.8</v>
    <v date="1983-05">73.8</v>
    <v date="1983-06">26.7</v>
    <v date="1983-07">16.3</v>
    <v date="1983-08">62.1</v>
    <v date="1983-09">38.3</v>
    <v date="1983-10">23.2</v>
    <v date="1983-11">46.0</v>
    <v date="1983-12">42.8</v>
    <v date="1984-01">65.2</v>
    <v date="1984-02">53.5</v>
    <v date="1984-03">25.4</v>
    <v date="1984-04">53.7</v>
    <v date="1984-05">91.9</v>
    <v date="1984-06">57.7</v>
    <v date="1984-07">94.9</v>
    <v date="1984-08">22.6</v>
    <v date="1984-09">99.5</v>
    <v date="1984-10">63.8</v>
    <v date="1984-11">47.4</v>
    <v date="1984-12">25.0</v>
    <v date="1985-01">50.4</v>
    <v date="1985-02">23.1</v>
    <v date="1985-03">41.3</v>
    <v date="1985-04">57.5</v>
    <v date="1985-05">58.9</v>
    <v date="1985-06">103.1</v>
    <v date="1985-07">80.6</v>
    <v date="1985-08">43.8</v>
    <v date="1985-09">31.6</v>
    <v date="1985-10">22.4</v>
    <v date="1985-11">53.0</v>
    <v date="1985-12">85.0</v>
    <v date="1986-01">89.4</v>
    <v date="1986-02">32.0</v>
    <v date="1986-03">76.0</v>
    <v date="1986-04">58.8</v>
    <v date="1986-05">70.2</v>
    <v date="1986-06">58.8</v>
    <v date="1986-07">41.6</v>
    <v date="1986-08">59.8</v>
    <v date="1986-09">62.3</v>
    <v date="1986-10">73.8</v>
    <v date="1986-11">17.9</v>
    <v date="1986-12">92.2</v>
    <v date="1987-01">131.7</v>
    <v date="1987-02">33.3</v>
    <v date="1987-03">86.0</v>
    <v date="1987-04">25.3</v>
    <v date="1987-05">82.8</v>
    <v date="1987-06">114.4</v>
    <v date="1987-07">84.4</v>
    <v date="1987-08">68.4</v>
    <v date="1987-09">65.7</v>
    <v date="1987-10">31.7</v>
    <v date="1987-11">53.6</v>
    <v date="1987-12">29.0</v>
    <v date="1988-01">48.1</v>
    <v date="1988-02">74.7</v>
    <v date="1988-03">116.9</v>
    <v date="1988-04">17.6</v>
    <v date="1988-05">10.4</v>
    <v date="1988-06">24.1</v>
    <v date="1988-07">65.6</v>
    <v date="1988-08">29.5</v>
    <v date="1988-09">48.3</v>
    <v date="1988-10">20.8</v>
    <v date="1988-11">53.6</v>
    <v date="1988-12">120.1</v>
    <v date="1989-01">17.7</v>
    <v date="1989-02">32.9</v>
    <v date="1989-03">59.3</v>
    <v date="1989-04">40.7</v>
    <v date="1989-05">24.5</v>
    <v date="1989-06">75.1</v>
    <v date="1989-07">37.0</v>
    <v date="1989-08">34.6</v>
    <v date="1989-09">43.1</v>
    <v date="1989-10">51.1</v>
    <v date="1989-11">59.1</v>
    <v date="1989-12">67.6</v>
    <v date="1990-01">25.3</v>
    <v date="1990-02">75.3</v>
    <v date="1990-03">20.7</v>
    <v date="1990-04">36.5</v>
    <v date="1990-05">16.3</v>
    <v date="1990-06">101.0</v>
    <v date="1990-07">26.8</v>
    <v date="1990-08">52.7</v>
    <v date="1990-09">68.5</v>
    <v date="1990-10">21.9</v>
    <v date="1990-11">90.7</v>
    <v date="1990-12">68.8</v>
    <v date="1991-01">32.2</v>
    <v date="1991-02">30.2</v>
    <v date="1991-03">33.4</v>
    <v date="1991-04">26.9</v>
    <v date="1991-05">20.4</v>
    <v date="1991-06">62.8</v>
    <v date="1991-07">77.2</v>
    <v date="1991-08">30.4</v>
    <v date="1991-09">32.2</v>
    <v date="1991-10">31.9</v>
    <v date="1991-11">42.5</v>
    <v date="1991-12">71.0</v>
    <v date="1992-01">28.3</v>
    <v date="1992-02">28.1</v>
    <v date="1992-03">76.5</v>
    <v date="1992-04">26.8</v>
    <v date="1992-05">33.4</v>
    <v date="1992-06">105.8</v>
    <v date="1992-07">91.7</v>
    <v date="1992-08">57.2</v>
    <v date="1992-09">26.1</v>
    <v date="1992-10">71.3</v>
    <v date="1992-11">69.3</v>
    <v date="1992-12">54.6</v>
    <v date="1993-01">89.8</v>
    <v date="1993-02">21.8</v>
    <v date="1993-03">17.8</v>
    <v date="1993-04">42.2</v>
    <v date="1993-05">71.1</v>
    <v date="1993-06">107.3</v>
    <v date="1993-07">116.3</v>
    <v date="1993-08">43.3</v>
    <v date="1993-09">49.9</v>
    <v date="1993-10">42.6</v>
    <v date="1993-11">37.5</v>
    <v date="1993-12">112.6</v>
    <v date="1994-01">74.0</v>
    <v date="1994-02">33.7</v>
    <v date="1994-03">118.4</v>
    <v date="1994-04">77.6</v>
    <v date="1994-05">74.7</v>
    <v date="1994-06">36.2</v>
    <v date="1994-07">50.2</v>
    <v date="1994-08">100.0</v>
    <v date="1994-09">61.1</v>
    <v date="1994-10">39.4</v>
    <v date="1994-11">54.2</v>
    <v date="1994-12">49.4</v>
    <v date="1995-01">104.8</v>
    <v date="1995-02">54.4</v>
    <v date="1995-03">44.7</v>
    <v date="1995-04">63.3</v>
    <v date="1995-05">88.9</v>
    <v date="1995-06">44.4</v>
    <v date="1995-07">37.9</v>
    <v date="1995-08">44.9</v>
    <v date="1995-09">80.3</v>
    <v date="1995-10">4.7</v>
    <v date="1995-11">53.2</v>
    <v date="1995-12" geoQualityLevel="certain" sensorHeightAboveGround="1">40.7</v>
    <v date="1996-01">3.8</v>
    <v date="1996-02">48.3</v>
    <v date="1996-03">19.3</v>
    <v date="1996-04">36.9</v>
    <v date="1996-05">79.8</v>
    <v date="1996-06">34.2</v>
    <v date="1996-07">53.9</v>
    <v date="1996-08">121.5</v>
    <v date="1996-09">41.0</v>
    <v date="1996-10">97.0</v>
    <v date="1996-11">76.2</v>
    <v date="1996-12">53.9</v>
    <v date="1997-01">12.5</v>
    <v date="1997-02">87.3</v>
    <v date="1997-03">59.1</v>
    <v date="1997-04">36.7</v>
    <v date="1997-05">73.9</v>
    <v date="1997-06">56.3</v>
    <v date="1997-07">77.4</v>
    <v date="1997-08">31.9</v>
    <v date="1997-09">11.7</v>
    <v date="1997-10">71.2</v>
    <v date="1997-11">45.0</v>
    <v date="1997-12">75.7</v>
    <v date="1998-01">44.7</v>
    <v date="1998-02">13.1</v>
    <v date="1998-03">70.5</v>
    <v date="1998-04">78.4</v>
    <v date="1998-05">24.0</v>
    <v date="1998-06">41.1</v>
    <v date="1998-07">84.8</v>
    <v date="1998-08">62.1</v>
    <v date="1998-09">117.1</v>
    <v date="1998-10">168.4</v>
    <v date="1998-11">73.5</v>
    <v date="1998-12">35.8</v>
    <v date="1999-01">56.9</v>
    <v date="1999-02">80.4</v>
    <v date="1999-03">52.9</v>
    <v date="1999-04">57.6</v>
    <v date="1999-05">65.7</v>
    <v date="1999-06">92.5</v>
    <v date="1999-07">83.9</v>
    <v date="1999-08">56.1</v>
    <v date="1999-09">33.1</v>
    <v date="1999-10">34.4</v>
    <v date="1999-11">57.8</v>
    <v date="1999-12">103.2</v>
    <v date="2000-01">61.3</v>
    <v date="2000-02">90.6</v>
    <v date="2000-03">110.6</v>
    <v date="2000-04">22.6</v>
    <v date="2000-05">47.2</v>
    <v date="2000-06">51.3</v>
    <v date="2000-07">61.1</v>
    <v date="2000-08">46.2</v>
    <v date="2000-09">53.0</v>
    <v date="2000-10">37.8</v>
    <v date="2000-11">45.8</v>
    <v date="2000-12">50.5</v>
    <v date="2001-01">54.5</v>
    <v date="2001-02">38.6</v>
    <v date="2001-03">103.0</v>
    <v date="2001-04">41.0</v>
    <v date="2001-05">30.7</v>
    <v date="2001-06">63.5</v>
    <v date="2001-07">87.5</v>
    <v date="2001-08">31.4</v>
    <v date="2001-09">116.9</v>
    <v date="2001-10">31.3</v>
    <v date="2001-11">61.5</v>
    <v date="2001-12">83.7</v>
    <v date="2002-01">35.3</v>
    <v date="2002-02">109.0</v>
    <v date="2002-03">64.3</v>
    <v date="2002-04">52.3</v>
    <v date="2002-05">57.5</v>
    <v date="2002-06">50.3</v>
    <v date="2002-07">143.9</v>
    <v date="2002-08">113.3</v>
    <v date="2002-09">43.8</v>
    <v date="2002-10">103.6</v>
    <v date="2002-11">110.2</v>
    <v date="2002-12">110.8</v>
    <v date="2003-01">75.9</v>
    <v date="2003-02">15.9</v>
    <v date="2003-03">29.5</v>
    <v date="2003-04">43.1</v>
    <v date="2003-05">49.4</v>
    <v date="2003-06">32.1</v>
    <v date="2003-07">24.2</v>
    <v date="2003-08">24.9</v>
    <v date="2003-09">62.6</v>
    <v date="2003-10">40.8</v>
    <v date="2003-11">43.0</v>
    <v date="2003-12">69.9</v>
    <v date="2004-01">78.4</v>
    <v date="2004-02">59.9</v>
    <v date="2004-03">35.3</v>
    <v date="2004-04">46.7</v>
    <v date="2004-05">81.7</v>
    <v date="2004-06">69.8</v>
    <v date="2004-07">116.6</v>
    <v date="2004-08">56.9</v>
    <v date="2004-09">57.6</v>
    <v date="2004-10">20.4</v>
    <v date="2004-11">91.3</v>
    <v date="2004-12">36.3</v>
    <v date="2005-01">92.9</v>
    <v date="2005-02">58.7</v>
    <v date="2005-03">32.7</v>
    <v date="2005-04">68.5</v>
    <v date="2005-05">93.2</v>
    <v date="2005-06">52.3</v>
    <v date="2005-07">58.2</v>
    <v date="2005-08">40.8</v>
    <v date="2005-09">38.4</v>
    <v date="2005-10">28.5</v>
    <v date="2005-11">51.5</v>
    <v date="2005-12">65.4</v>
    <v date="2006-01">26.4</v>
    <v date="2006-02">68.4</v>
    <v date="2006-03">80.1</v>
    <v date="2006-04">44.3</v>
    <v date="2006-05">103.3</v>
    <v date="2006-06">23.1</v>
    <v date="2006-07">89.4</v>
    <v date="2006-08">103.5</v>
    <v date="2006-09">9.3</v>
    <v date="2006-10">38.9</v>
    <v date="2006-11">50.3</v>
    <v date="2006-12">31.0</v>
    <v date="2007-01">89.4</v>
    <v date="2007-02">79.9</v>
    <v date="2007-03">67.0</v>
    <v date="2007-04">5.5</v>
    <v date="2007-05">132.8</v>
    <v date="2007-06">97.1</v>
    <v date="2007-07">120.1</v>
    <v date="2007-08">67.9</v>
    <v date="2007-09">132.9</v>
    <v date="2007-10">24.2</v>
    <v date="2007-11">84.6</v>
    <v date="2007-12">44.0</v>
    <v date="2008-01">64.7</v>
    <v date="2008-02">36.0</v>
    <v date="2008-03">66.3</v>
    <v date="2008-04">66.6</v>
    <v date="2008-05">16.5</v>
    <v date="2008-06">69.6</v>
    <v date="2008-07">97.9</v>
    <v date="2008-08">31.3</v>
    <v date="2008-09">52.6</v>
    <v date="2008-10">49.4</v>
    <v date="2008-11">51.2</v>
    <v date="2008-12">49.4</v>
    <v date="2009-01">39.9</v>
    <v date="2009-02">71.7</v>
    <v date="2009-03">77.4</v>
    <v date="2009-04">43.4</v>
    <v date="2009-05">58.5</v>
    <v date="2009-06">38.9</v>
    <v date="2009-07">99.3</v>
    <v date="2009-08">44.7</v>
    <v date="2009-09">85.1</v>
    <v date="2009-10">60.8</v>
    <v date="2009-11">91.5</v>
    <v date="2009-12">98.0</v>
    <v date="2010-01">38.9</v>
    <v date="2010-02">38.5</v>
    <v date="2010-03">53.3</v>
    <v date="2010-04">17.6</v>
    <v date="2010-05">95.7</v>
    <v date="2010-06">29.0</v>
    <v date="2010-07">52.7</v>
    <v date="2010-08">191.4</v>
    <v date="2010-09">76.3</v>
    <v date="2010-10">24.5</v>
    <v date="2010-11">94.3</v>
    <v date="2010-12">76.4</v>
    <v date="2011-01">46.1</v>
    <v date="2011-02">15.1</v>
    <v date="2011-03">14.3</v>
    <v date="2011-04">25.3</v>
    <v date="2011-05">22.9</v>
    <v date="2011-06">82.6</v>
    <v date="2011-07">52.3</v>
    <v date="2011-08">65.2</v>
    <v date="2011-09">46.8</v>
    <v date="2011-10">43.3</v>
    <v date="2011-11">0.6</v>
    <v date="2011-12">100.2</v>
</stationname>
</data>